cri_simulations/FPGA_Execution/__init__.py
cri_simulations/FPGA_Execution/base_functions.py
cri_simulations/FPGA_Execution/fpga_compiler.py
cri_simulations/FPGA_Execution/fpga_controller.py
cri_simulations/__init__.py
cri_simulations/api.py
cri_simulations/compile_network.py
cri_simulations/config.py
cri_simulations/config.yaml
cri_simulations/network.py
cri_simulations/utils.py
cri_simulations-1.2.1.dist-info/WHEEL
cri_simulations-1.2.1.dist-info/METADATA
cri_simulations-1.2.1.dist-info/RECORD
