Metadata-Version: 2.1
Name: cri-simulations
Version: 1.2.1
Summary: Software for interacting with the CRI neuromorphic hardware
Author: Justin Frank
Requires-Python: >=3.9,<3.11
Classifier: Programming Language :: Python :: 3
Classifier: Programming Language :: Python :: 3.10
Classifier: Programming Language :: Python :: 3.9
Requires-Dist: PyMetis (>=2020.1,<2021.0)
Requires-Dist: bidict (>=0.22.0,<0.23.0)
Requires-Dist: click (>=8.1.3,<9.0.0)
Requires-Dist: confuse (>=1.7.0,<2.0.0)
Requires-Dist: fbpca (>=1.0,<2.0)
Requires-Dist: k-means-constrained (>=0.7.1,<0.8.0)
Requires-Dist: matplotlib (>=3.5.2,<4.0.0)
Requires-Dist: metis (>=0.2a5,<0.3)
Requires-Dist: networkx (>=2.8.3,<3.0.0)
Requires-Dist: numpy (>=1.18)
Requires-Dist: scipy (>=1.8.1,<2.0.0)
Requires-Dist: sklearn (>=0.0,<0.1)
